{
  "$schema": "https://developer.microsoft.com/json-schemas/fabric/item/report/definition/visualContainer/2.5.0/schema.json",
  "name": "email-combo1",
  "position": {
    "x": 0,
    "y": 80,
    "z": 6000,
    "width": 827,
    "height": 200,
    "tabOrder": 6
  },
  "visual": {
    "visualType": "lineClusteredColumnComboChart",
    "query": {
      "queryState": {}
    },
    "objects": {
      "categoryAxis": [
        {
          "properties": {
            "show": {
              "expr": {
                "Literal": {
                  "Value": "true"
                }
              }
            },
            "showAxisTitle": {
              "expr": {
                "Literal": {
                  "Value": "false"
                }
              }
            },
            "innerPadding": {
              "expr": {
                "Literal": {
                  "Value": "62.5L"
                }
              }
            }
          }
        }
      ],
      "valueAxis": [
        {
          "properties": {
            "show": {
              "expr": {
                "Literal": {
                  "Value": "true"
                }
              }
            },
            "showAxisTitle": {
              "expr": {
                "Literal": {
                  "Value": "false"
                }
              }
            },
            "invertAxis": {
              "expr": {
                "Literal": {
                  "Value": "false"
                }
              }
            },
            "gridlineShow": {
              "expr": {
                "Literal": {
                  "Value": "false"
                }
              }
            },
            "gridlineStyle": {
              "expr": {
                "Literal": {
                  "Value": "'solid'"
                }
              }
            },
            "secShow": {
              "expr": {
                "Literal": {
                  "Value": "true"
                }
              }
            },
            "secShowAxisTitle": {
              "expr": {
                "Literal": {
                  "Value": "false"
                }
              }
            }
          }
        }
      ],
      "legend": [
        {
          "properties": {
            "show": {
              "expr": {
                "Literal": {
                  "Value": "true"
                }
              }
            },
            "position": {
              "expr": {
                "Literal": {
                  "Value": "'Top'"
                }
              }
            }
          }
        }
      ],
      "labels": [
        {
          "properties": {
            "show": {
              "expr": {
                "Literal": {
                  "Value": "false"
                }
              }
            },
            "labelPosition": {
              "expr": {
                "Literal": {
                  "Value": "'Under'"
                }
              }
            },
            "enableTitleDataLabel": {
              "expr": {
                "Literal": {
                  "Value": "false"
                }
              }
            },
            "fontSize": {
              "expr": {
                "Literal": {
                  "Value": "8D"
                }
              }
            }
          }
        }
      ],
      "lineStyles": [
        {
          "properties": {
            "lineStyle": {
              "expr": {
                "Literal": {
                  "Value": "'solid'"
                }
              }
            },
            "lineChartType": {
              "expr": {
                "Literal": {
                  "Value": "'smooth'"
                }
              }
            },
            "strokeWidth": {
              "expr": {
                "Literal": {
                  "Value": "1L"
                }
              }
            },
            "showMarker": {
              "expr": {
                "Literal": {
                  "Value": "true"
                }
              }
            },
            "markerSize": {
              "expr": {
                "Literal": {
                  "Value": "4D"
                }
              }
            }
          }
        }
      ],
      "dataPoint": [
        {
          "properties": {
            "fill": {
              "solid": {
                "color": {
                  "expr": {
                    "Literal": {
                      "Value": "'#12239E'"
                    }
                  }
                }
              }
            }
          },
          "selector": {
            "metadata": "Sum(Sales.Profit)"
          }
        },
        {
          "properties": {
            "fill": {
              "solid": {
                "color": {
                  "expr": {
                    "Literal": {
                      "Value": "'#118DFF'"
                    }
                  }
                }
              }
            }
          }
        }
      ],
      "title": [
        {
          "properties": {
            "show": {
              "expr": {
                "Literal": {
                  "Value": "true"
                }
              }
            },
            "text": {
              "expr": {
                "Literal": {
                  "Value": "'Emails Sent & Conversion Rate'"
                }
              }
            },
            "fontColor": {
              "solid": {
                "color": {
                  "expr": {
                    "Literal": {
                      "Value": "'#252423'"
                    }
                  }
                }
              }
            },
            "fontSize": {
              "expr": {
                "Literal": {
                  "Value": "12L"
                }
              }
            }
          }
        }
      ]
    },
    "drillFilterOtherVisuals": true
  }
}